setup.cfg
setup.py
sphinx_gettext_helper/__init__.py
sphinx_gettext_helper/command.py
sphinx_gettext_helper.egg-info/PKG-INFO
sphinx_gettext_helper.egg-info/SOURCES.txt
sphinx_gettext_helper.egg-info/dependency_links.txt
sphinx_gettext_helper.egg-info/entry_points.txt
sphinx_gettext_helper.egg-info/namespace_packages.txt
sphinx_gettext_helper.egg-info/not-zip-safe
sphinx_gettext_helper.egg-info/requires.txt
sphinx_gettext_helper.egg-info/top_level.txt