Metadata-Version: 1.0
Name: sphinx-gettext-helper
Version: 0.1.3
Summary: gettext helper script for Sphinx
Home-page: http://bitbucket.org/tk0miya/sphinx-gettext-helper
Author: Takeshi Komiya
Author-email: i.tkomiya@gmail.com
License: BSD
Download-URL: http://pypi.python.org/pypi/sphinx-gettext-helper
Platform: any
Classifier: Development Status :: 4 - Beta
Classifier: Environment :: Console
Classifier: Environment :: Web Environment
Classifier: Intended Audience :: Developers
Classifier: License :: OSI Approved :: BSD License
Classifier: Operating System :: OS Independent
Classifier: Programming Language :: Python
Classifier: Topic :: Documentation
Classifier: Topic :: Utilities
